Metadata-Version: 1.0
Name: dsnd-prob-basic
Version: 0.1
Summary: Gaussian distributions
Home-page: UNKNOWN
Author: Ahmed Mohsen
Author-email: UNKNOWN
License: UNKNOWN
Platform: UNKNOWN
